zeitdieb.py
zeitdieb-0.3.1.dist-info/WHEEL
zeitdieb-0.3.1.dist-info/METADATA
zeitdieb-0.3.1.dist-info/RECORD
