Metadata-Version: 2.1
Name: zeitdieb
Version: 0.3.1
Summary: 
Author: Patrick Schemitz
Author-email: ps@solute.de
Requires-Python: >=3.9,<4.0
Classifier: Programming Language :: Python :: 3
Classifier: Programming Language :: Python :: 3.10
Classifier: Programming Language :: Python :: 3.9
